sceptic/__init__.py
sceptic/evaluation.py
sceptic/plotting.py
sceptic/sceptic.py
sceptic-0.4.0.dist-info/METADATA
sceptic-0.4.0.dist-info/WHEEL
sceptic-0.4.0.dist-info/licenses/LICENSE
sceptic-0.4.0.dist-info/RECORD
