Metadata-Version: 2.4
Name: sceptic
Version: 0.4.0
Summary: Pseudotime analysis for time-series single-cell sequencing and imaging data
Project-URL: Homepage, https://github.com/Noble-Lab/Sceptic
Project-URL: Bug Tracker, https://github.com/Noble-Lab/Sceptic/issues
Author-email: Gang Li <gangliuw@uw.edu>
License-File: LICENSE
Classifier: License :: OSI Approved :: MIT License
Classifier: Operating System :: OS Independent
Classifier: Programming Language :: Python :: 3
Requires-Python: >=3.7
Requires-Dist: matplotlib
Requires-Dist: numpy
Requires-Dist: packaging
Requires-Dist: pandas
Requires-Dist: scikit-learn
Requires-Dist: scipy
Requires-Dist: seaborn
Requires-Dist: svm
Requires-Dist: xgboost
